pycutest/__init__.py
pycutest/build_interface.py
pycutest/c_interface.py
pycutest/install_scripts.py
pycutest/problem_class.py
pycutest/python_interface.py
pycutest/sifdecode_extras.py
pycutest/system_paths.py
pycutest-1.7.2.dist-info/LICENSE
pycutest-1.7.2.dist-info/METADATA
pycutest-1.7.2.dist-info/WHEEL
pycutest-1.7.2.dist-info/top_level.txt
pycutest-1.7.2.dist-info/RECORD
