Metadata-Version: 2.1
Name: pycutest
Version: 1.7.2
Summary: A Python wrapper to the CUTEst optimization test environment
Author-email: Jaroslav Fowkes <jaroslav.fowkes@maths.ox.ac.uk>, Lindon Roberts <lindon.roberts@sydney.edu.au>
Maintainer-email: Jaroslav Fowkes <jaroslav.fowkes@maths.ox.ac.uk>, Lindon Roberts <lindon.roberts@sydney.edu.au>
License: GPL-3.0-or-later
Project-URL: Homepage, https://github.com/jfowkes/pycutest/
Project-URL: Download, https://github.com/jfowkes/pycutest/releases/
Project-URL: Bug Tracker, https://github.com/jfowkes/pycutest/issues/
Project-URL: Documentation, https://jfowkes.github.io/pycutest/
Project-URL: Source Code, https://github.com/jfowkes/pycutest/
Keywords: mathematics,optimization
Classifier: Development Status :: 5 - Production/Stable
Classifier: Environment :: Console
Classifier: Framework :: IPython
Classifier: Framework :: Jupyter
Classifier: Intended Audience :: Science/Research
Classifier: License :: OSI Approved :: GNU General Public License v3 or later (GPLv3+)
Classifier: Operating System :: MacOS
Classifier: Operating System :: Unix
Classifier: Programming Language :: Python
Classifier: Programming Language :: Python :: 3
Classifier: Programming Language :: Python :: 3.8
Classifier: Programming Language :: Python :: 3.9
Classifier: Programming Language :: Python :: 3.10
Classifier: Programming Language :: Python :: 3.11
Classifier: Programming Language :: Python :: 3.12
Classifier: Topic :: Scientific/Engineering
Classifier: Topic :: Scientific/Engineering :: Mathematics
Requires-Python: >=3.8
License-File: LICENSE
Requires-Dist: setuptools
Requires-Dist: numpy
Requires-Dist: scipy
